k_general_kit/__init__.py
k_general_kit/eval_sequence.py
k_general_kit/gen_func.py
k_general_kit/gen_obj.py
k_general_kit/search_sort/__init__.py
k_general_kit/search_sort/heap.py
k_general_kit/search_sort/search_sort.py
k_general_kit-1.2.0.dist-info/METADATA
k_general_kit-1.2.0.dist-info/WHEEL
k_general_kit-1.2.0.dist-info/licenses/LICENSE
k_general_kit-1.2.0.dist-info/RECORD
