Metadata-Version: 2.3
Name: k_general_kit
Version: 1.2.0
Summary: A package with some usual general functions and objects
Project-URL: Homepage, https://pypi.org/project/k-general-kit/
Project-URL: Issues, https://github.com/KpihX/k_general_kit/issues
Project-URL: Repository, https://github.com/KpihX/k_general_kit.git
Author-email: KpihX <kapoivha@gmail.com>
Maintainer-email: KpihX <kapoivha@gmail.com>
License: MIT License
License-File: LICENSE
Keywords: containers,general,search,sort,tools
Classifier: Development Status :: 4 - Beta
Classifier: Intended Audience :: Developers
Classifier: License :: OSI Approved :: MIT License
Classifier: Operating System :: OS Independent
Classifier: Programming Language :: Python :: 3
Requires-Python: >=3.8
